spelling_bee/__init__.py
spelling_bee/spelling_bee.py
spelling_bee_mh-0.0.0.dist-info/LICENSE
spelling_bee_mh-0.0.0.dist-info/METADATA
spelling_bee_mh-0.0.0.dist-info/WHEEL
spelling_bee_mh-0.0.0.dist-info/top_level.txt
spelling_bee_mh-0.0.0.dist-info/RECORD
