Metadata-Version: 2.1
Name: spelling-bee-mh
Version: 0.0.0
Summary: code to cheat on New York Times Spelling Bee Game
Home-page: https://github.com/mharty3/spelling_bee_package_tutorial
Maintainer: Michael Harty
License: UNKNOWN
Platform: UNKNOWN
License-File: LICENSE
Requires-Dist: requests
Requires-Dist: importlib-metadata ; python_version < "3.8"
